scitex/__init__.py
scitex/__main__.py
scitex/__version__.py
scitex/_sh.py
scitex/errors.py
scitex/units.py
scitex/ai/__init__.py
scitex/ai/_gen_ai/_Anthropic.py
scitex/ai/_gen_ai/_BaseGenAI.py
scitex/ai/_gen_ai/_DeepSeek.py
scitex/ai/_gen_ai/_Google.py
scitex/ai/_gen_ai/_Groq.py
scitex/ai/_gen_ai/_Llama.py
scitex/ai/_gen_ai/_OpenAI.py
scitex/ai/_gen_ai/_PARAMS.py
scitex/ai/_gen_ai/_Perplexity.py
scitex/ai/_gen_ai/__init__.py
scitex/ai/_gen_ai/_calc_cost.py
scitex/ai/_gen_ai/_format_output_func.py
scitex/ai/_gen_ai/_genai_factory.py
scitex/ai/activation/__init__.py
scitex/ai/activation/_define.py
scitex/ai/classification/Classifier.py
scitex/ai/classification/CrossValidationExperiment.py
scitex/ai/classification/__init__.py
scitex/ai/classification/reporters/_BaseClassificationReporter.py
scitex/ai/classification/reporters/_ClassificationReporter.py
scitex/ai/classification/reporters/_MultiClassificationReporter.py
scitex/ai/classification/reporters/_SingleClassificationReporter.py
scitex/ai/classification/reporters/__init__.py
scitex/ai/classification/reporters/reporter_utils/_Plotter.py
scitex/ai/classification/reporters/reporter_utils/__init__.py
scitex/ai/classification/reporters/reporter_utils/aggregation.py
scitex/ai/classification/reporters/reporter_utils/data_models.py
scitex/ai/classification/reporters/reporter_utils/reporting.py
scitex/ai/classification/reporters/reporter_utils/storage.py
scitex/ai/classification/reporters/reporter_utils/validation.py
scitex/ai/classification/timeseries/_TimeSeriesBlockingSplit.py
scitex/ai/classification/timeseries/_TimeSeriesCalendarSplit.py
scitex/ai/classification/timeseries/_TimeSeriesMetadata.py
scitex/ai/classification/timeseries/_TimeSeriesSlidingWindowSplit.py
scitex/ai/classification/timeseries/_TimeSeriesSlidingWindowSplit_v01-not-using-n_splits.py
scitex/ai/classification/timeseries/_TimeSeriesStrategy.py
scitex/ai/classification/timeseries/_TimeSeriesStratifiedSplit.py
scitex-2.1.0.dist-info/LICENSE
scitex-2.1.0.dist-info/METADATA
scitex-2.1.0.dist-info/WHEEL
scitex-2.1.0.dist-info/entry_points.txt
scitex-2.1.0.dist-info/top_level.txt
scitex-2.1.0.dist-info/RECORD
