Metadata-Version: 2.1
Name: scitex
Version: 2.1.0
Summary: A comprehensive scientific computing framework for Python
Home-page: https://github.com/ywatanabe1989/SciTeX-Code
Author: Yusuke Watanabe
Author-email: ywatanabe@scitex.ai
License: UNKNOWN
Project-URL: Bug Tracker, https://github.com/ywatanabe1989/scitex/issues
Project-URL: Documentation, https://scitex.readthedocs.io
Project-URL: Source Code, https://github.com/ywatanabe1989/scitex
Keywords: scientific computing,data analysis,machine learning,visualization,research
Platform: UNKNOWN
Classifier: Development Status :: 4 - Beta
Classifier: Intended Audience :: Science/Research
Classifier: Intended Audience :: Developers
Classifier: License :: OSI Approved :: MIT License
Classifier: Programming Language :: Python :: 3
Classifier: Programming Language :: Python :: 3.8
Classifier: Programming Language :: Python :: 3.9
Classifier: Programming Language :: Python :: 3.10
Classifier: Programming Language :: Python :: 3.11
Classifier: Programming Language :: Python :: 3.12
Classifier: Topic :: Scientific/Engineering
Classifier: Topic :: Scientific/Engineering :: Artificial Intelligence
Classifier: Topic :: Scientific/Engineering :: Visualization
Classifier: Topic :: Software Development :: Libraries :: Python Modules
Requires-Python: >=3.8
License-File: LICENSE
Requires-Dist: GitPython
Requires-Dist: Pillow
Requires-Dist: PyMuPDF
Requires-Dist: PyPDF2
Requires-Dist: PyYAML
Requires-Dist: Pyarrow
Requires-Dist: accelerate
Requires-Dist: aiohttp
Requires-Dist: ansi-escapes
Requires-Dist: anthropic
Requires-Dist: attrdict
Requires-Dist: autopep8
Requires-Dist: bitsandbytes
Requires-Dist: black
Requires-Dist: bs4
Requires-Dist: build
Requires-Dist: catboost
Requires-Dist: chardet
Requires-Dist: click
Requires-Dist: crawl4ai
Requires-Dist: docutils<0.18
Requires-Dist: einops
Requires-Dist: fairscale
Requires-Dist: fastapi
Requires-Dist: flake8
Requires-Dist: flask
Requires-Dist: geom-median
Requires-Dist: google-genai
Requires-Dist: google-search-results
Requires-Dist: googlesearch-python
Requires-Dist: groq
Requires-Dist: h5py
Requires-Dist: html2text
Requires-Dist: icecream
Requires-Dist: imbalanced-learn
Requires-Dist: impact-factor
Requires-Dist: ipdb
Requires-Dist: ipykernel
Requires-Dist: ipython
Requires-Dist: isort
Requires-Dist: jedi
Requires-Dist: joblib
Requires-Dist: joypy
Requires-Dist: julius
Requires-Dist: jupyter-collaboration
Requires-Dist: jupyterlab
Requires-Dist: jupytext
Requires-Dist: line-profiler
Requires-Dist: llama-stack
Requires-Dist: lxml
Requires-Dist: lxml-html-clean
Requires-Dist: markdown
Requires-Dist: markdown2
Requires-Dist: matplotlib
Requires-Dist: memory-profiler
Requires-Dist: mne
Requires-Dist: more-itertools
Requires-Dist: mypy
Requires-Dist: myst-parser
Requires-Dist: natsort
Requires-Dist: nbsphinx
Requires-Dist: nest-asyncio
Requires-Dist: numpy
Requires-Dist: obspy
Requires-Dist: openai
Requires-Dist: opencv-python
Requires-Dist: openpyxl
Requires-Dist: optuna
Requires-Dist: packaging
Requires-Dist: pandas
Requires-Dist: papermill
Requires-Dist: pdfplumber
Requires-Dist: pebble
Requires-Dist: platformdirs
Requires-Dist: plotly
Requires-Dist: plyer
Requires-Dist: pre-commit
Requires-Dist: psutil
Requires-Dist: psycopg2-binary
Requires-Dist: pyautogui
Requires-Dist: pybids
Requires-Dist: pyedflib
Requires-Dist: pygments
Requires-Dist: pylint
Requires-Dist: pyls
Requires-Dist: pymatreader
Requires-Dist: pymed
Requires-Dist: pyperclip
Requires-Dist: pyright
Requires-Dist: pytesseract
Requires-Dist: pytest
Requires-Dist: pytest-asyncio
Requires-Dist: pytest-cov
Requires-Dist: pytest-env
Requires-Dist: pytest-mock
Requires-Dist: pytest-testmon
Requires-Dist: pytest-timeout
Requires-Dist: pytest-xdist
Requires-Dist: python-docx
Requires-Dist: python-lsp-server
Requires-Dist: python-magic
Requires-Dist: pytorch-optimizer
Requires-Dist: pytorch-pretrained-vit
Requires-Dist: pyupgrade
Requires-Dist: readability
Requires-Dist: readability-lxml
Requires-Dist: readchar
Requires-Dist: reportlab
Requires-Dist: requests
Requires-Dist: ripple-detection
Requires-Dist: rope
Requires-Dist: ruamel.yaml
Requires-Dist: ruff-lsp
Requires-Dist: scholarly
Requires-Dist: scikit-image
Requires-Dist: scikit-learn
Requires-Dist: scipy
Requires-Dist: seaborn
Requires-Dist: selenium
Requires-Dist: setuptools
Requires-Dist: six
Requires-Dist: sktime
Requires-Dist: sounddevice
Requires-Dist: sphinx
Requires-Dist: sphinx-autobuild
Requires-Dist: sphinx-autodoc-typehints
Requires-Dist: sphinx-rtd-theme
Requires-Dist: sql-manager
Requires-Dist: sqlalchemy
Requires-Dist: statsmodels
Requires-Dist: streamlit
Requires-Dist: sympy
Requires-Dist: tabulate
Requires-Dist: tensorpac
Requires-Dist: termplotlib
Requires-Dist: thefuzz
Requires-Dist: timeout-decorator
Requires-Dist: tk
Requires-Dist: tldr
Requires-Dist: torch
Requires-Dist: torchaudio
Requires-Dist: torchsummary
Requires-Dist: torchvision
Requires-Dist: transformers
Requires-Dist: twine
Requires-Dist: types-PyYAML
Requires-Dist: types-requests
Requires-Dist: types-setuptools
Requires-Dist: umap-learn
Requires-Dist: webdriver-manager
Requires-Dist: webrequests
Requires-Dist: wheel
Requires-Dist: xarray
Requires-Dist: xlrd
Requires-Dist: xmltodict
Requires-Dist: zarr
Provides-Extra: dev
Requires-Dist: black; extra == "dev"
Requires-Dist: flake8; extra == "dev"
Requires-Dist: isort; extra == "dev"
Requires-Dist: pytest; extra == "dev"
Requires-Dist: pytest-cov; extra == "dev"
Requires-Dist: sphinx; extra == "dev"
Provides-Extra: docs
Requires-Dist: sphinx; extra == "docs"
Requires-Dist: sphinx-autodoc-typehints; extra == "docs"
Requires-Dist: sphinx-rtd-theme; extra == "docs"
